setup.py
flask/__init__.py
flask/skels/__init__.py
flask/skels/package.py
flask_tmpl.egg-info/PKG-INFO
flask_tmpl.egg-info/SOURCES.txt
flask_tmpl.egg-info/dependency_links.txt
flask_tmpl.egg-info/entry_points.txt
flask_tmpl.egg-info/namespace_packages.txt
flask_tmpl.egg-info/requires.txt
flask_tmpl.egg-info/top_level.txt