Metadata-Version: 1.1
Name: flask-tmpl
Version: 0.2.0
Summary: PasteScript templates for the Flask+Celery+SQLAlchemy
Home-page: https://liuliqiang.info/docs/flask-tmpl
Author: yetship
Author-email: liqianglau@outlook.com
License: MIT
Keywords: flask paste templates
Platform: UNKNOWN
Classifier: Programming Language :: Python
Classifier: Programming Language :: Python :: 2.7
Classifier: Topic :: Software Development :: Libraries :: Python Modules
